pyxdiamond
