Metadata-Version: 1.0
Name: pyxdiamond
Version: 1.0.1
Summary: xdiamond sdk
Home-page: UNKNOWN
Author: lockeCucumber
Author-email: lockeCucumber@163.com
License: MIT Licence
Keywords: pip,datacanvas,xdiamond,lockeCucumber
Platform: any
